ootkintercanvas/__init__.py
ootkintercanvas/oocanvas.py
ootkintercanvas-0.3.5.dist-info/LICENSE
ootkintercanvas-0.3.5.dist-info/METADATA
ootkintercanvas-0.3.5.dist-info/WHEEL
ootkintercanvas-0.3.5.dist-info/top_level.txt
ootkintercanvas-0.3.5.dist-info/RECORD
